kroger_api/__init__.py
kroger_api/client.py
kroger_api/kroger_api.py
kroger_api/token_storage.py
kroger_api/api/__init__.py
kroger_api/api/authorization.py
kroger_api/api/cart.py
kroger_api/api/identity.py
kroger_api/api/location.py
kroger_api/api/product.py
kroger_api/auth/__init__.py
kroger_api/auth/interactive.py
kroger_api/utils/__init__.py
kroger_api/utils/env.py
kroger_api/utils/oauth.py
kroger_api/utils/pkce.py
kroger_api-0.2.0.dist-info/licenses/LICENSE
kroger_api-0.2.0.dist-info/METADATA
kroger_api-0.2.0.dist-info/WHEEL
kroger_api-0.2.0.dist-info/top_level.txt
kroger_api-0.2.0.dist-info/RECORD
