Metadata-Version: 2.4
Name: kroger-api
Version: 0.2.0
Summary: A Python client library for the Kroger Public API
Home-page: https://github.com/CupOfOwls/kroger-api
Author: Stephen Thoemmes
Author-email: Stephen Thoemmes <thoemmes.stephen@gmail.com>
License: MIT License
Project-URL: Homepage, https://github.com/CupOfOwls/kroger-api
Project-URL: Repository, https://github.com/CupOfOwls/kroger-api
Project-URL: Documentation, https://developer.kroger.com/documentation/public/
Project-URL: Bug Reports, https://github.com/CupOfOwls/kroger-api/issues
Project-URL: Demo Video, https://github.com/CupOfOwls/kroger-api/blob/main/assets/kroger-api-python-add-to-cart-demo.mp4
Keywords: kroger,api,grocery,shopping,retail
Classifier: Development Status :: 4 - Beta
Classifier: Intended Audience :: Developers
Classifier: License :: OSI Approved :: MIT License
Classifier: Operating System :: OS Independent
Classifier: Programming Language :: Python :: 3
Classifier: Programming Language :: Python :: 3.8
Classifier: Programming Language :: Python :: 3.9
Classifier: Programming Language :: Python :: 3.10
Classifier: Programming Language :: Python :: 3.11
Classifier: Programming Language :: Python :: 3.12
Classifier: Topic :: Software Development :: Libraries :: Python Modules
Classifier: Topic :: Internet :: WWW/HTTP :: Dynamic Content
Classifier: Topic :: Office/Business
Requires-Python: >=3.8
License-File: LICENSE
Requires-Dist: requests>=2.25.0
Requires-Dist: python-dotenv>=0.15.0
Requires-Dist: certifi>=2021.0.0
Requires-Dist: urllib3>=1.26.0
Provides-Extra: dev
Requires-Dist: pytest>=7.0.0; extra == "dev"
Requires-Dist: pytest-mock>=3.0.0; extra == "dev"
Requires-Dist: requests-mock>=1.9.0; extra == "dev"
Requires-Dist: black; extra == "dev"
Requires-Dist: flake8; extra == "dev"
Requires-Dist: mypy; extra == "dev"
Provides-Extra: examples
Requires-Dist: tabulate>=0.8.0; extra == "examples"
Dynamic: author
Dynamic: home-page
Dynamic: license-file
Dynamic: requires-python
